acappella_info/__init__.py
acappella_info/_version.py
acappella_info/utils.py
acappella_info/csv_files/__init__.py
acappella_info/csv_files/full_dataset.csv
acappella_info/csv_files/test_seen.csv
acappella_info/csv_files/test_unseen.csv
acappella_info/csv_files/train.csv
acappella_info/csv_files/val_seen.csv
acappella_info/json_files/__init__.py
acappella_info/json_files/acapella_all.json
acappella_info/json_files/acapella_english_fem.json
acappella_info/json_files/acapella_info_from_ids.json
acappella_info/json_files/acapella_info_ordered.json
acappella_info/json_files/acapella_timestamps.json
acappella_info/json_files/splits.json
acappella_info-0.1.post1.dist-info/METADATA
acappella_info-0.1.post1.dist-info/WHEEL
acappella_info-0.1.post1.dist-info/top_level.txt
acappella_info-0.1.post1.dist-info/RECORD
