Metadata-Version: 2.1
Name: acappella-info
Version: 0.1.post1
Summary: Python implementation of  Acappella Dataset
Home-page: UNKNOWN
Author: Juan Montesinos
Author-email: juanfelipe.montesinos@upf.edu
License: UNKNOWN
Platform: UNKNOWN
Classifier: Programming Language :: Python :: 3
